descope/__init__.py
descope/_auth_base.py
descope/_http_base.py
descope/auth.py
descope/authmethod/__init__.py
descope/authmethod/enchantedlink.py
descope/authmethod/magiclink.py
descope/authmethod/oauth.py
descope/authmethod/otp.py
descope/authmethod/password.py
descope/authmethod/saml.py
descope/authmethod/sso.py
descope/authmethod/totp.py
descope/authmethod/webauthn.py
descope/common.py
descope/descope_client.py
descope/exceptions.py
descope/flask/__init__.py
descope/http_client.py
descope/jwt_common.py
descope/management/access_key.py
descope/management/audit.py
descope/management/authz.py
descope/management/common.py
descope/management/descoper.py
descope/management/fga.py
descope/management/flow.py
descope/management/group.py
descope/management/jwt.py
descope/management/management_key.py
descope/management/outbound_application.py
descope/management/permission.py
descope/management/project.py
descope/management/role.py
descope/management/sso_application.py
descope/management/sso_settings.py
descope/management/tenant.py
descope/management/user.py
descope/management/user_pwd.py
descope/mgmt.py
descope/py.typed
descope-1.10.0.dist-info/METADATA
descope-1.10.0.dist-info/WHEEL
descope-1.10.0.dist-info/licenses/LICENSE
descope-1.10.0.dist-info/RECORD
