Metadata-Version: 2.4
Name: descope
Version: 1.10.0
Summary: Descope Python SDK
License: MIT
License-File: LICENSE
Author: Descope
Author-email: info@descope.com
Requires-Python: >=3.8.1,<4.0
Classifier: Development Status :: 5 - Production/Stable
Classifier: Intended Audience :: Developers
Classifier: License :: OSI Approved :: MIT License
Classifier: Operating System :: OS Independent
Classifier: Programming Language :: Python
Classifier: Programming Language :: Python :: 3
Classifier: Programming Language :: Python :: 3.9
Classifier: Programming Language :: Python :: 3.10
Classifier: Programming Language :: Python :: 3.11
Classifier: Programming Language :: Python :: 3.12
Classifier: Programming Language :: Python :: 3.13
Classifier: Programming Language :: Python :: 3.14
Classifier: Programming Language :: Python :: 3 :: Only
Classifier: Programming Language :: Python :: 3.8
Classifier: Topic :: Software Development :: Libraries :: Python Modules
Classifier: Typing :: Typed
Provides-Extra: flask
Requires-Dist: Flask (>=2) ; extra == "flask"
Requires-Dist: email-validator (>=2,<3) ; python_version >= "3.8"
Requires-Dist: liccheck (>=0.9.1,<0.10.0)
Requires-Dist: pyjwt[crypto] (>=2.4.0)
Requires-Dist: requests (>=2.27.0)
Project-URL: Bug Tracker, https://github.com/descope/python-sdk/issues
Project-URL: Documentation, https://docs.descope.com
Project-URL: Homepage, https://descope.com/
Project-URL: Repository, https://github.com/descope/python-sdk
